Metadata-Version: 2.1
Name: scikit-geo
Version: 2.1.3
Summary: scikit geography
Author: Zijie Wang
